<?xml version="1.0" encoding="UTF-8"?>
<con:testCase id="e4358d97-5c38-4c42-87b5-5c71dfa66984" discardOkResults="false" failOnError="true" failTestCaseOnErrors="true" keepSession="false" name="Copy of RetrieveShopperReport" searchProperties="true" timeout="0" maxResults="0" xmlns:con="http://eviware.com/soapui/config">
  <con:settings>
    <con:setting id="e4358d97-5c38-4c42-87b5-5c71dfa66984fileName">Copy-of-RetrieveShopperReport</con:setting>
  </con:settings>
  <con:savedRecentRuns>1</con:savedRecentRuns>
  <con:testStep type="datasource" name="DataSource - RetrieveShopperReport" id="1dd533d6-938a-4cb6-86fb-d3f642abea0c">
    <con:settings/>
    <con:config xsi:type="con:DataSourceStep" xmlns:xsi="http://www.w3.org/2001/XMLSchema-instance">
      <con:dataSource type="Excel">
        <con:configuration>
          <file>Management_Rest_Input.xlsx</file>
          <worksheet>RetrieveShopperReport</worksheet>
          <cell>A1</cell>
          <ignoreEmpty>false</ignoreEmpty>
          <evaluateFormulas>false</evaluateFormulas>
        </con:configuration>
      </con:dataSource>
      <con:shared>true</con:shared>
      <con:restartShared>true</con:restartShared>
      <con:property>S.No</con:property>
      <con:property>ServiceName</con:property>
      <con:property>Operation Name</con:property>
      <con:property>ExecutionFlag</con:property>
      <con:property>TestCaseName</con:property>
      <con:property>TestCaseDescription</con:property>
      <con:property>application</con:property>
      <con:property>brand</con:property>
      <con:property>domainId</con:property>
      <con:property>uuid</con:property>
      <con:property>language</con:property>
      <con:property>startDate</con:property>
      <con:property>endDate</con:property>
      <con:property>reportType</con:property>
      <con:startRow>1</con:startRow>
      <con:endRow>2</con:endRow>
      <con:recordsPerIteration>1</con:recordsPerIteration>
      <con:completeLastOperation>true</con:completeLastOperation>
      <con:trimValues>false</con:trimValues>
      <con:entitizeValues>false</con:entitizeValues>
      <con:restartOnRun>true</con:restartOnRun>
      <con:expandProperties>false</con:expandProperties>
      <con:stopDatasourceExhausted>false</con:stopDatasourceExhausted>
    </con:config>
  </con:testStep>
  <con:testStep type="restrequest" name="retrieveShopperReport" id="e32932f9-3176-4f7f-9e75-5d1c6e413ac7" disabled="true">
    <con:settings/>
    <con:config service="ManagementOperations" resourcePath="/retrieveShopperReports" methodName="V2.0" xsi:type="con:RestRequestStep" xmlns:xsi="http://www.w3.org/2001/XMLSchema-instance">
      <con:restRequest name="retrieveShopperReport" id="db66adc3-3ed9-477b-9744-1759a4d4f7d8" mediaType="application/json">
        <con:settings>
          <con:setting id="com.eviware.soapui.impl.wsdl.WsdlRequest@request-headers">&lt;entry key="AppKey" value="${#Project#AppKey}" xmlns="http://eviware.com/soapui/config"/></con:setting>
        </con:settings>
        <con:endpoint>http://eslbservicestst01.rccl.com:14060</con:endpoint>
        <con:request/>
        <con:originalUri>http://eslbservicestst01.rccl.com/esl/management/rest/v2.0/retrieveShopperReports</con:originalUri>
        <con:assertion type="JsonPath Match" id="beae52e4-7bfd-4389-b11a-2ff5057010aa" name="Match content of [status]">
          <con:configuration>
            <path>$['header']['status']</path>
            <content>Success</content>
            <allowWildcards>false</allowWildcards>
            <ignoreNamspaceDifferences>false</ignoreNamspaceDifferences>
            <ignoreComments>false</ignoreComments>
          </con:configuration>
        </con:assertion>
        <con:assertion type="JsonPath Existence Match" id="96012648-a98d-4637-a85f-a8dbf2ab42c6" name="Check for existence of [shopperReport]">
          <con:configuration>
            <path>$['shopperReport']</path>
            <content>true</content>
            <allowWildcards>false</allowWildcards>
            <ignoreNamspaceDifferences>false</ignoreNamspaceDifferences>
            <ignoreComments>false</ignoreComments>
          </con:configuration>
        </con:assertion>
        <con:credentials>
          <con:selectedAuthProfile>No Authorization</con:selectedAuthProfile>
          <con:authType>No Authorization</con:authType>
        </con:credentials>
        <con:jmsConfig JMSDeliveryMode="PERSISTENT"/>
        <con:parameters>
          <con:entry key="reportType" value="CREATED"/>
          <con:entry key="header.application" value="${DataSource - RetrieveShopperReport#application}"/>
          <con:entry key="endDate" value="${DataSource - RetrieveShopperReport#endDate}"/>
          <con:entry key="header.domainId" value="${DataSource - RetrieveShopperReport#domainId}"/>
          <con:entry key="header.brand" value="${DataSource - RetrieveShopperReport#brand}"/>
          <con:entry key="startDate" value="${DataSource - RetrieveShopperReport#startDate}"/>
        </con:parameters>
        <con:parameterOrder>
          <con:entry>header.application</con:entry>
          <con:entry>header.brand</con:entry>
          <con:entry>header.domainId</con:entry>
          <con:entry>startDate</con:entry>
          <con:entry>reportType</con:entry>
        </con:parameterOrder>
        <con:environmentSpec>
          <con:entry environmentId="f907e159-4f0d-4708-bdcf-b78c5982a6cb">
            <con:authProfile>Inherit From Parent</con:authProfile>
          </con:entry>
          <con:entry environmentId="a80c7255-ad17-4b2e-8850-1b0cf8eb0cab">
            <con:authProfile>Inherit From Parent</con:authProfile>
          </con:entry>
          <con:entry environmentId="27b93fe3-7a99-411c-b585-a205c1d804df">
            <con:authProfile>No Authorization</con:authProfile>
          </con:entry>
          <con:entry environmentId="28f5cb4c-5c38-4fa1-8d65-c65701f30db4">
            <con:authProfile>Inherit From Parent</con:authProfile>
          </con:entry>
          <con:entry environmentId="b184688a-3391-458c-9cbf-28a1da9e06a5">
            <con:authProfile>Inherit From Parent</con:authProfile>
          </con:entry>
          <con:entry environmentId="cd2d1d50-3d3b-4639-b0c6-3b31a67a9065">
            <con:authProfile>Inherit From Parent</con:authProfile>
          </con:entry>
          <con:entry environmentId="4bea7faf-e188-475f-865a-c9aa0f297bb6">
            <con:authProfile>Inherit From Parent</con:authProfile>
          </con:entry>
          <con:entry environmentId="82661830-2f21-4684-b011-82797624551e">
            <con:authProfile>Inherit From Parent</con:authProfile>
          </con:entry>
          <con:entry environmentId="5cc641f7-5758-4418-9f14-1ea4e090d44f">
            <con:authProfile>Inherit From Parent</con:authProfile>
          </con:entry>
          <con:entry environmentId="c2fbd171-bae5-4d21-8308-36b0f0cec128">
            <con:authProfile>Inherit From Parent</con:authProfile>
          </con:entry>
          <con:entry environmentId="134218be-1c27-418c-8bd6-12e4d94d4285">
            <con:authProfile>Inherit From Parent</con:authProfile>
          </con:entry>
          <con:entry environmentId="57fba944-b31a-4195-a863-9fdc0de72c06">
            <con:authProfile>No Authorization</con:authProfile>
          </con:entry>
          <con:entry environmentId="fe4ac908-2759-4f3a-abc8-9e08ff64ebd8">
            <con:authProfile>No Authorization</con:authProfile>
          </con:entry>
          <con:entry environmentId="23242ad3-e1f8-4800-b06c-451f8d968909">
            <con:authProfile>No Authorization</con:authProfile>
          </con:entry>
          <con:entry environmentId="ff71313a-41b8-4d4d-a809-083489049364">
            <con:authProfile>Inherit From Parent</con:authProfile>
          </con:entry>
          <con:entry environmentId="754fc145-88a5-4748-85e0-639ebb8fded6">
            <con:authProfile>Inherit From Parent</con:authProfile>
          </con:entry>
          <con:entry environmentId="be9208f1-b1d6-440e-a939-d2f7cc136e96">
            <con:authProfile>Inherit From Parent</con:authProfile>
          </con:entry>
          <con:entry environmentId="1526d4e5-9a23-44ee-b20e-7ae834bbe614">
            <con:authProfile>Inherit From Parent</con:authProfile>
          </con:entry>
          <con:entry environmentId="31a41053-178b-4763-b482-d62fec86e414">
            <con:authProfile>Inherit From Parent</con:authProfile>
          </con:entry>
          <con:entry environmentId="7a18fa54-e460-4770-9c83-8ab558505d1a">
            <con:authProfile>Inherit From Parent</con:authProfile>
          </con:entry>
          <con:entry environmentId="e879c8b5-9d9f-46b5-816f-1e2462d463e9">
            <con:authProfile>Inherit From Parent</con:authProfile>
          </con:entry>
          <con:entry environmentId="1840a87b-48e2-4fa0-a5d4-13045f9fed1a">
            <con:authProfile>Inherit From Parent</con:authProfile>
          </con:entry>
          <con:entry environmentId="2be189eb-0ab1-4c9f-ad42-84486b8e2e56">
            <con:authProfile>Inherit From Parent</con:authProfile>
          </con:entry>
          <con:entry environmentId="0f1e39eb-2c73-476f-88da-c2f9200ee160">
            <con:authProfile>Inherit From Parent</con:authProfile>
          </con:entry>
          <con:entry environmentId="da4da12c-07ab-4206-acf3-1bc119bfa803">
            <con:authProfile>Inherit From Parent</con:authProfile>
          </con:entry>
          <con:entry environmentId="fc1d9e4e-4d88-49b3-9cb3-ef4210009f89">
            <con:authProfile>Inherit From Parent</con:authProfile>
          </con:entry>
          <con:entry environmentId="53516c62-e8e0-4b88-b003-4c0e2aa8dbd3">
            <con:authProfile>Inherit From Parent</con:authProfile>
          </con:entry>
          <con:entry environmentId="0fbe5b0b-a38f-4b5d-a073-1256bff7bd99">
            <con:authProfile>Inherit From Parent</con:authProfile>
          </con:entry>
        </con:environmentSpec>
      </con:restRequest>
    </con:config>
  </con:testStep>
  <con:testStep type="restrequest" name="retrieveShopperReport - without Brand" id="8e485d77-a010-470c-8b70-4b00b069737e">
    <con:settings/>
    <con:config service="ManagementOperations" resourcePath="/retrieveShopperReports" methodName="V2.0" xsi:type="con:RestRequestStep" xmlns:xsi="http://www.w3.org/2001/XMLSchema-instance">
      <con:restRequest name="retrieveShopperReport - without Brand" id="db66adc3-3ed9-477b-9744-1759a4d4f7d8" mediaType="application/json">
        <con:settings>
          <con:setting id="com.eviware.soapui.impl.wsdl.WsdlRequest@request-headers">&lt;entry key="AppKey" value="${#Project#AppKey}" xmlns="http://eviware.com/soapui/config"/></con:setting>
        </con:settings>
        <con:endpoint>http://eslbservicestst01.rccl.com:14060</con:endpoint>
        <con:request/>
        <con:originalUri>http://eslbservicestst01.rccl.com/esl/management/rest/v2.0/retrieveShopperReports</con:originalUri>
        <con:assertion type="JsonPath Match" id="beae52e4-7bfd-4389-b11a-2ff5057010aa" name="Match content of [status]">
          <con:configuration>
            <path>$['header']['status']</path>
            <content>Failure</content>
            <allowWildcards>false</allowWildcards>
            <ignoreNamspaceDifferences>false</ignoreNamspaceDifferences>
            <ignoreComments>false</ignoreComments>
          </con:configuration>
        </con:assertion>
        <con:assertion type="JsonPath Match" id="0f723a9b-8cb7-4859-8d8f-297856d84699" name="Match content of [description]">
          <con:configuration>
            <path>$['header']['error'][0]['description']</path>
            <content>Value is required for brandCode</content>
            <allowWildcards>false</allowWildcards>
            <ignoreNamspaceDifferences>false</ignoreNamspaceDifferences>
            <ignoreComments>false</ignoreComments>
          </con:configuration>
        </con:assertion>
        <con:credentials>
          <con:selectedAuthProfile>No Authorization</con:selectedAuthProfile>
          <con:authType>No Authorization</con:authType>
        </con:credentials>
        <con:jmsConfig JMSDeliveryMode="PERSISTENT"/>
        <con:parameters>
          <con:entry key="reportType" value="CREATED"/>
          <con:entry key="header.application" value="${DataSource - RetrieveShopperReport#application}"/>
          <con:entry key="endDate" value="${DataSource - RetrieveShopperReport#endDate}"/>
          <con:entry key="header.domainId" value="${DataSource - RetrieveShopperReport#domainId}"/>
          <con:entry key="startDate" value="${DataSource - RetrieveShopperReport#startDate}"/>
        </con:parameters>
        <con:parameterOrder>
          <con:entry>header.application</con:entry>
          <con:entry>header.brand</con:entry>
          <con:entry>header.domainId</con:entry>
          <con:entry>startDate</con:entry>
          <con:entry>reportType</con:entry>
        </con:parameterOrder>
        <con:environmentSpec>
          <con:entry environmentId="f907e159-4f0d-4708-bdcf-b78c5982a6cb">
            <con:authProfile>Inherit From Parent</con:authProfile>
          </con:entry>
          <con:entry environmentId="a80c7255-ad17-4b2e-8850-1b0cf8eb0cab">
            <con:authProfile>Inherit From Parent</con:authProfile>
          </con:entry>
          <con:entry environmentId="27b93fe3-7a99-411c-b585-a205c1d804df">
            <con:authProfile>No Authorization</con:authProfile>
          </con:entry>
          <con:entry environmentId="28f5cb4c-5c38-4fa1-8d65-c65701f30db4">
            <con:authProfile>Inherit From Parent</con:authProfile>
          </con:entry>
          <con:entry environmentId="b184688a-3391-458c-9cbf-28a1da9e06a5">
            <con:authProfile>Inherit From Parent</con:authProfile>
          </con:entry>
          <con:entry environmentId="cd2d1d50-3d3b-4639-b0c6-3b31a67a9065">
            <con:authProfile>Inherit From Parent</con:authProfile>
          </con:entry>
          <con:entry environmentId="4bea7faf-e188-475f-865a-c9aa0f297bb6">
            <con:authProfile>Inherit From Parent</con:authProfile>
          </con:entry>
          <con:entry environmentId="82661830-2f21-4684-b011-82797624551e">
            <con:authProfile>Inherit From Parent</con:authProfile>
          </con:entry>
          <con:entry environmentId="5cc641f7-5758-4418-9f14-1ea4e090d44f">
            <con:authProfile>Inherit From Parent</con:authProfile>
          </con:entry>
          <con:entry environmentId="c2fbd171-bae5-4d21-8308-36b0f0cec128">
            <con:authProfile>Inherit From Parent</con:authProfile>
          </con:entry>
          <con:entry environmentId="134218be-1c27-418c-8bd6-12e4d94d4285">
            <con:authProfile>Inherit From Parent</con:authProfile>
          </con:entry>
          <con:entry environmentId="57fba944-b31a-4195-a863-9fdc0de72c06">
            <con:authProfile>No Authorization</con:authProfile>
          </con:entry>
          <con:entry environmentId="fe4ac908-2759-4f3a-abc8-9e08ff64ebd8">
            <con:authProfile>No Authorization</con:authProfile>
          </con:entry>
          <con:entry environmentId="23242ad3-e1f8-4800-b06c-451f8d968909">
            <con:authProfile>No Authorization</con:authProfile>
          </con:entry>
          <con:entry environmentId="ff71313a-41b8-4d4d-a809-083489049364">
            <con:authProfile>Inherit From Parent</con:authProfile>
          </con:entry>
          <con:entry environmentId="754fc145-88a5-4748-85e0-639ebb8fded6">
            <con:authProfile>Inherit From Parent</con:authProfile>
          </con:entry>
          <con:entry environmentId="be9208f1-b1d6-440e-a939-d2f7cc136e96">
            <con:authProfile>Inherit From Parent</con:authProfile>
          </con:entry>
          <con:entry environmentId="1526d4e5-9a23-44ee-b20e-7ae834bbe614">
            <con:authProfile>Inherit From Parent</con:authProfile>
          </con:entry>
          <con:entry environmentId="31a41053-178b-4763-b482-d62fec86e414">
            <con:authProfile>Inherit From Parent</con:authProfile>
          </con:entry>
          <con:entry environmentId="7a18fa54-e460-4770-9c83-8ab558505d1a">
            <con:authProfile>Inherit From Parent</con:authProfile>
          </con:entry>
          <con:entry environmentId="e879c8b5-9d9f-46b5-816f-1e2462d463e9">
            <con:authProfile>Inherit From Parent</con:authProfile>
          </con:entry>
          <con:entry environmentId="1840a87b-48e2-4fa0-a5d4-13045f9fed1a">
            <con:authProfile>Inherit From Parent</con:authProfile>
          </con:entry>
          <con:entry environmentId="2be189eb-0ab1-4c9f-ad42-84486b8e2e56">
            <con:authProfile>Inherit From Parent</con:authProfile>
          </con:entry>
          <con:entry environmentId="0f1e39eb-2c73-476f-88da-c2f9200ee160">
            <con:authProfile>Inherit From Parent</con:authProfile>
          </con:entry>
          <con:entry environmentId="da4da12c-07ab-4206-acf3-1bc119bfa803">
            <con:authProfile>Inherit From Parent</con:authProfile>
          </con:entry>
          <con:entry environmentId="fc1d9e4e-4d88-49b3-9cb3-ef4210009f89">
            <con:authProfile>Inherit From Parent</con:authProfile>
          </con:entry>
          <con:entry environmentId="53516c62-e8e0-4b88-b003-4c0e2aa8dbd3">
            <con:authProfile>Inherit From Parent</con:authProfile>
          </con:entry>
          <con:entry environmentId="0fbe5b0b-a38f-4b5d-a073-1256bff7bd99">
            <con:authProfile>Inherit From Parent</con:authProfile>
          </con:entry>
        </con:environmentSpec>
      </con:restRequest>
    </con:config>
  </con:testStep>
  <con:testStep type="restrequest" name="retrieveShopperReport - wrong StartDate Format" id="f94a1fdb-e5d7-4489-b2a2-e35ff723bc8d">
    <con:settings/>
    <con:config service="ManagementOperations" resourcePath="/retrieveShopperReports" methodName="V2.0" xsi:type="con:RestRequestStep" xmlns:xsi="http://www.w3.org/2001/XMLSchema-instance">
      <con:restRequest name="retrieveShopperReport - wrong StartDate Format" id="db66adc3-3ed9-477b-9744-1759a4d4f7d8" mediaType="application/json">
        <con:settings>
          <con:setting id="com.eviware.soapui.impl.wsdl.WsdlRequest@request-headers">&lt;entry key="AppKey" value="${#Project#AppKey}" xmlns="http://eviware.com/soapui/config"/></con:setting>
        </con:settings>
        <con:endpoint>http://eslbservicestst01.rccl.com:14060</con:endpoint>
        <con:request/>
        <con:originalUri>http://eslbservicestst01.rccl.com/esl/management/rest/v2.0/retrieveShopperReports</con:originalUri>
        <con:assertion type="JsonPath Match" id="beae52e4-7bfd-4389-b11a-2ff5057010aa" name="Match content of [status]">
          <con:configuration>
            <path>$['header']['status']</path>
            <content>Failure</content>
            <allowWildcards>false</allowWildcards>
            <ignoreNamspaceDifferences>false</ignoreNamspaceDifferences>
            <ignoreComments>false</ignoreComments>
          </con:configuration>
        </con:assertion>
        <con:assertion type="JsonPath Match" id="f994e734-cf21-409e-85ca-669c9ff95af1" name="Match content of [component]">
          <con:configuration>
            <path>$['header']['error'][0]['component']</path>
            <content>BaseOrchestration</content>
            <allowWildcards>false</allowWildcards>
            <ignoreNamspaceDifferences>false</ignoreNamspaceDifferences>
            <ignoreComments>false</ignoreComments>
          </con:configuration>
        </con:assertion>
        <con:credentials>
          <con:selectedAuthProfile>No Authorization</con:selectedAuthProfile>
          <con:authType>No Authorization</con:authType>
        </con:credentials>
        <con:jmsConfig JMSDeliveryMode="PERSISTENT"/>
        <con:parameters>
          <con:entry key="reportType" value="CREATED"/>
          <con:entry key="header.application" value="${DataSource - RetrieveShopperReport#application}"/>
          <con:entry key="endDate" value="${DataSource - RetrieveShopperReport#endDate}"/>
          <con:entry key="header.domainId" value="${DataSource - RetrieveShopperReport#domainId}"/>
          <con:entry key="header.brand" value="${DataSource - RetrieveShopperReport#brand}"/>
          <con:entry key="startDate" value="1234"/>
        </con:parameters>
        <con:parameterOrder>
          <con:entry>header.application</con:entry>
          <con:entry>header.brand</con:entry>
          <con:entry>header.domainId</con:entry>
          <con:entry>startDate</con:entry>
          <con:entry>reportType</con:entry>
        </con:parameterOrder>
        <con:environmentSpec>
          <con:entry environmentId="f907e159-4f0d-4708-bdcf-b78c5982a6cb">
            <con:authProfile>Inherit From Parent</con:authProfile>
          </con:entry>
          <con:entry environmentId="a80c7255-ad17-4b2e-8850-1b0cf8eb0cab">
            <con:authProfile>Inherit From Parent</con:authProfile>
          </con:entry>
          <con:entry environmentId="27b93fe3-7a99-411c-b585-a205c1d804df">
            <con:authProfile>No Authorization</con:authProfile>
          </con:entry>
          <con:entry environmentId="28f5cb4c-5c38-4fa1-8d65-c65701f30db4">
            <con:authProfile>Inherit From Parent</con:authProfile>
          </con:entry>
          <con:entry environmentId="b184688a-3391-458c-9cbf-28a1da9e06a5">
            <con:authProfile>Inherit From Parent</con:authProfile>
          </con:entry>
          <con:entry environmentId="cd2d1d50-3d3b-4639-b0c6-3b31a67a9065">
            <con:authProfile>Inherit From Parent</con:authProfile>
          </con:entry>
          <con:entry environmentId="4bea7faf-e188-475f-865a-c9aa0f297bb6">
            <con:authProfile>Inherit From Parent</con:authProfile>
          </con:entry>
          <con:entry environmentId="82661830-2f21-4684-b011-82797624551e">
            <con:authProfile>Inherit From Parent</con:authProfile>
          </con:entry>
          <con:entry environmentId="5cc641f7-5758-4418-9f14-1ea4e090d44f">
            <con:authProfile>Inherit From Parent</con:authProfile>
          </con:entry>
          <con:entry environmentId="c2fbd171-bae5-4d21-8308-36b0f0cec128">
            <con:authProfile>Inherit From Parent</con:authProfile>
          </con:entry>
          <con:entry environmentId="134218be-1c27-418c-8bd6-12e4d94d4285">
            <con:authProfile>Inherit From Parent</con:authProfile>
          </con:entry>
          <con:entry environmentId="57fba944-b31a-4195-a863-9fdc0de72c06">
            <con:authProfile>No Authorization</con:authProfile>
          </con:entry>
          <con:entry environmentId="fe4ac908-2759-4f3a-abc8-9e08ff64ebd8">
            <con:authProfile>No Authorization</con:authProfile>
          </con:entry>
          <con:entry environmentId="23242ad3-e1f8-4800-b06c-451f8d968909">
            <con:authProfile>No Authorization</con:authProfile>
          </con:entry>
          <con:entry environmentId="ff71313a-41b8-4d4d-a809-083489049364">
            <con:authProfile>Inherit From Parent</con:authProfile>
          </con:entry>
          <con:entry environmentId="754fc145-88a5-4748-85e0-639ebb8fded6">
            <con:authProfile>Inherit From Parent</con:authProfile>
          </con:entry>
          <con:entry environmentId="be9208f1-b1d6-440e-a939-d2f7cc136e96">
            <con:authProfile>Inherit From Parent</con:authProfile>
          </con:entry>
          <con:entry environmentId="1526d4e5-9a23-44ee-b20e-7ae834bbe614">
            <con:authProfile>Inherit From Parent</con:authProfile>
          </con:entry>
          <con:entry environmentId="31a41053-178b-4763-b482-d62fec86e414">
            <con:authProfile>Inherit From Parent</con:authProfile>
          </con:entry>
          <con:entry environmentId="7a18fa54-e460-4770-9c83-8ab558505d1a">
            <con:authProfile>Inherit From Parent</con:authProfile>
          </con:entry>
          <con:entry environmentId="e879c8b5-9d9f-46b5-816f-1e2462d463e9">
            <con:authProfile>Inherit From Parent</con:authProfile>
          </con:entry>
          <con:entry environmentId="1840a87b-48e2-4fa0-a5d4-13045f9fed1a">
            <con:authProfile>Inherit From Parent</con:authProfile>
          </con:entry>
          <con:entry environmentId="2be189eb-0ab1-4c9f-ad42-84486b8e2e56">
            <con:authProfile>Inherit From Parent</con:authProfile>
          </con:entry>
          <con:entry environmentId="0f1e39eb-2c73-476f-88da-c2f9200ee160">
            <con:authProfile>Inherit From Parent</con:authProfile>
          </con:entry>
          <con:entry environmentId="da4da12c-07ab-4206-acf3-1bc119bfa803">
            <con:authProfile>Inherit From Parent</con:authProfile>
          </con:entry>
          <con:entry environmentId="fc1d9e4e-4d88-49b3-9cb3-ef4210009f89">
            <con:authProfile>Inherit From Parent</con:authProfile>
          </con:entry>
          <con:entry environmentId="53516c62-e8e0-4b88-b003-4c0e2aa8dbd3">
            <con:authProfile>Inherit From Parent</con:authProfile>
          </con:entry>
          <con:entry environmentId="0fbe5b0b-a38f-4b5d-a073-1256bff7bd99">
            <con:authProfile>Inherit From Parent</con:authProfile>
          </con:entry>
        </con:environmentSpec>
      </con:restRequest>
    </con:config>
  </con:testStep>
  <con:testStep type="restrequest" name="retrieveShopperReport - invalid reportType" id="5ccad5e3-a4db-47ee-a5f1-2d865689352e">
    <con:settings/>
    <con:config service="ManagementOperations" resourcePath="/retrieveShopperReports" methodName="V2.0" xsi:type="con:RestRequestStep" xmlns:xsi="http://www.w3.org/2001/XMLSchema-instance">
      <con:restRequest name="retrieveShopperReport - invalid reportType" id="db66adc3-3ed9-477b-9744-1759a4d4f7d8" mediaType="application/json">
        <con:settings>
          <con:setting id="com.eviware.soapui.impl.wsdl.WsdlRequest@request-headers">&lt;entry key="AppKey" value="${#Project#AppKey}" xmlns="http://eviware.com/soapui/config"/></con:setting>
        </con:settings>
        <con:endpoint>http://eslbservicestst01.rccl.com:14060</con:endpoint>
        <con:request/>
        <con:originalUri>http://eslbservicestst01.rccl.com/esl/management/rest/v2.0/retrieveShopperReports</con:originalUri>
        <con:assertion type="XPath Match" id="f2b9bc6f-a7c1-4b9d-9ee1-ab7c00b3e261" name="Match content of [title]">
          <con:configuration>
            <path>//html[1]/head[1]/title[1]/text()</path>
            <content>HTTP Status 400 – Bad Request</content>
            <allowWildcards>false</allowWildcards>
            <ignoreNamspaceDifferences>false</ignoreNamspaceDifferences>
            <ignoreComments>false</ignoreComments>
          </con:configuration>
        </con:assertion>
        <con:credentials>
          <con:selectedAuthProfile>No Authorization</con:selectedAuthProfile>
          <con:authType>No Authorization</con:authType>
        </con:credentials>
        <con:jmsConfig JMSDeliveryMode="PERSISTENT"/>
        <con:parameters>
          <con:entry key="reportType" value="1111"/>
          <con:entry key="header.application" value="${DataSource - RetrieveShopperReport#application}"/>
          <con:entry key="endDate" value="${DataSource - RetrieveShopperReport#endDate}"/>
          <con:entry key="header.domainId" value="${DataSource - RetrieveShopperReport#domainId}"/>
          <con:entry key="header.brand" value="${DataSource - RetrieveShopperReport#brand}"/>
          <con:entry key="startDate" value="${DataSource - RetrieveShopperReport#startDate}"/>
        </con:parameters>
        <con:parameterOrder>
          <con:entry>header.application</con:entry>
          <con:entry>header.brand</con:entry>
          <con:entry>header.domainId</con:entry>
          <con:entry>startDate</con:entry>
          <con:entry>reportType</con:entry>
        </con:parameterOrder>
        <con:environmentSpec>
          <con:entry environmentId="f907e159-4f0d-4708-bdcf-b78c5982a6cb">
            <con:authProfile>Inherit From Parent</con:authProfile>
          </con:entry>
          <con:entry environmentId="a80c7255-ad17-4b2e-8850-1b0cf8eb0cab">
            <con:authProfile>Inherit From Parent</con:authProfile>
          </con:entry>
          <con:entry environmentId="27b93fe3-7a99-411c-b585-a205c1d804df">
            <con:authProfile>No Authorization</con:authProfile>
          </con:entry>
          <con:entry environmentId="28f5cb4c-5c38-4fa1-8d65-c65701f30db4">
            <con:authProfile>Inherit From Parent</con:authProfile>
          </con:entry>
          <con:entry environmentId="b184688a-3391-458c-9cbf-28a1da9e06a5">
            <con:authProfile>Inherit From Parent</con:authProfile>
          </con:entry>
          <con:entry environmentId="cd2d1d50-3d3b-4639-b0c6-3b31a67a9065">
            <con:authProfile>Inherit From Parent</con:authProfile>
          </con:entry>
          <con:entry environmentId="4bea7faf-e188-475f-865a-c9aa0f297bb6">
            <con:authProfile>Inherit From Parent</con:authProfile>
          </con:entry>
          <con:entry environmentId="82661830-2f21-4684-b011-82797624551e">
            <con:authProfile>Inherit From Parent</con:authProfile>
          </con:entry>
          <con:entry environmentId="5cc641f7-5758-4418-9f14-1ea4e090d44f">
            <con:authProfile>Inherit From Parent</con:authProfile>
          </con:entry>
          <con:entry environmentId="c2fbd171-bae5-4d21-8308-36b0f0cec128">
            <con:authProfile>Inherit From Parent</con:authProfile>
          </con:entry>
          <con:entry environmentId="134218be-1c27-418c-8bd6-12e4d94d4285">
            <con:authProfile>Inherit From Parent</con:authProfile>
          </con:entry>
          <con:entry environmentId="57fba944-b31a-4195-a863-9fdc0de72c06">
            <con:authProfile>No Authorization</con:authProfile>
          </con:entry>
          <con:entry environmentId="fe4ac908-2759-4f3a-abc8-9e08ff64ebd8">
            <con:authProfile>No Authorization</con:authProfile>
          </con:entry>
          <con:entry environmentId="23242ad3-e1f8-4800-b06c-451f8d968909">
            <con:authProfile>No Authorization</con:authProfile>
          </con:entry>
          <con:entry environmentId="ff71313a-41b8-4d4d-a809-083489049364">
            <con:authProfile>Inherit From Parent</con:authProfile>
          </con:entry>
          <con:entry environmentId="754fc145-88a5-4748-85e0-639ebb8fded6">
            <con:authProfile>Inherit From Parent</con:authProfile>
          </con:entry>
          <con:entry environmentId="be9208f1-b1d6-440e-a939-d2f7cc136e96">
            <con:authProfile>Inherit From Parent</con:authProfile>
          </con:entry>
          <con:entry environmentId="1526d4e5-9a23-44ee-b20e-7ae834bbe614">
            <con:authProfile>Inherit From Parent</con:authProfile>
          </con:entry>
          <con:entry environmentId="31a41053-178b-4763-b482-d62fec86e414">
            <con:authProfile>Inherit From Parent</con:authProfile>
          </con:entry>
          <con:entry environmentId="7a18fa54-e460-4770-9c83-8ab558505d1a">
            <con:authProfile>Inherit From Parent</con:authProfile>
          </con:entry>
          <con:entry environmentId="e879c8b5-9d9f-46b5-816f-1e2462d463e9">
            <con:authProfile>Inherit From Parent</con:authProfile>
          </con:entry>
          <con:entry environmentId="1840a87b-48e2-4fa0-a5d4-13045f9fed1a">
            <con:authProfile>Inherit From Parent</con:authProfile>
          </con:entry>
          <con:entry environmentId="2be189eb-0ab1-4c9f-ad42-84486b8e2e56">
            <con:authProfile>Inherit From Parent</con:authProfile>
          </con:entry>
          <con:entry environmentId="0f1e39eb-2c73-476f-88da-c2f9200ee160">
            <con:authProfile>Inherit From Parent</con:authProfile>
          </con:entry>
          <con:entry environmentId="da4da12c-07ab-4206-acf3-1bc119bfa803">
            <con:authProfile>Inherit From Parent</con:authProfile>
          </con:entry>
          <con:entry environmentId="fc1d9e4e-4d88-49b3-9cb3-ef4210009f89">
            <con:authProfile>Inherit From Parent</con:authProfile>
          </con:entry>
          <con:entry environmentId="53516c62-e8e0-4b88-b003-4c0e2aa8dbd3">
            <con:authProfile>Inherit From Parent</con:authProfile>
          </con:entry>
          <con:entry environmentId="0fbe5b0b-a38f-4b5d-a073-1256bff7bd99">
            <con:authProfile>Inherit From Parent</con:authProfile>
          </con:entry>
        </con:environmentSpec>
      </con:restRequest>
    </con:config>
  </con:testStep>
  <con:testStep type="datasourceloop" name="DataSource Loop" id="8de219e4-a2da-42f8-bc44-cb560d147c85">
    <con:settings/>
    <con:config>
      <dataSourceStep>DataSource - RetrieveShopperReport</dataSourceStep>
      <targetStep>retrieveShopperReport</targetStep>
      <discardResults>true</discardResults>
    </con:config>
  </con:testStep>
  <con:properties/>
  <con:reportParameters/>
  <con:breakPoints>
    <con:testStepId>0f019135-73b4-44de-a9f1-d2c6ca55c195</con:testStepId>
    <con:status>NONE</con:status>
    <con:properties/>
  </con:breakPoints>
  <con:breakPoints>
    <con:testStepId>7ca9e64d-c258-4f12-8e55-a27ffb83f22c</con:testStepId>
    <con:status>NONE</con:status>
    <con:properties/>
  </con:breakPoints>
  <con:breakPoints>
    <con:testStepId>cdc38077-1394-4400-b8e4-ceab54e87a0e</con:testStepId>
    <con:status>NONE</con:status>
    <con:properties/>
  </con:breakPoints>
  <con:environmentSpec>
    <con:entry environmentId="b184688a-3391-458c-9cbf-28a1da9e06a5">
      <con:authProfile>Inherit From Parent</con:authProfile>
    </con:entry>
    <con:entry environmentId="cd2d1d50-3d3b-4639-b0c6-3b31a67a9065">
      <con:authProfile>Inherit From Parent</con:authProfile>
    </con:entry>
    <con:entry environmentId="ff71313a-41b8-4d4d-a809-083489049364">
      <con:authProfile>Inherit From Parent</con:authProfile>
    </con:entry>
    <con:entry environmentId="754fc145-88a5-4748-85e0-639ebb8fded6">
      <con:authProfile>Inherit From Parent</con:authProfile>
    </con:entry>
    <con:entry environmentId="be9208f1-b1d6-440e-a939-d2f7cc136e96">
      <con:authProfile>Inherit From Parent</con:authProfile>
    </con:entry>
    <con:entry environmentId="1526d4e5-9a23-44ee-b20e-7ae834bbe614">
      <con:authProfile>Inherit From Parent</con:authProfile>
    </con:entry>
    <con:entry environmentId="31a41053-178b-4763-b482-d62fec86e414">
      <con:authProfile>Inherit From Parent</con:authProfile>
    </con:entry>
    <con:entry environmentId="7a18fa54-e460-4770-9c83-8ab558505d1a">
      <con:authProfile>Inherit From Parent</con:authProfile>
    </con:entry>
    <con:entry environmentId="e879c8b5-9d9f-46b5-816f-1e2462d463e9">
      <con:authProfile>Inherit From Parent</con:authProfile>
    </con:entry>
    <con:entry environmentId="1840a87b-48e2-4fa0-a5d4-13045f9fed1a">
      <con:authProfile>Inherit From Parent</con:authProfile>
    </con:entry>
    <con:entry environmentId="2be189eb-0ab1-4c9f-ad42-84486b8e2e56">
      <con:authProfile>Inherit From Parent</con:authProfile>
    </con:entry>
    <con:entry environmentId="0f1e39eb-2c73-476f-88da-c2f9200ee160">
      <con:authProfile>Inherit From Parent</con:authProfile>
    </con:entry>
    <con:entry environmentId="da4da12c-07ab-4206-acf3-1bc119bfa803">
      <con:authProfile>Inherit From Parent</con:authProfile>
    </con:entry>
    <con:entry environmentId="fc1d9e4e-4d88-49b3-9cb3-ef4210009f89">
      <con:authProfile>Inherit From Parent</con:authProfile>
    </con:entry>
    <con:entry environmentId="53516c62-e8e0-4b88-b003-4c0e2aa8dbd3">
      <con:authProfile>Inherit From Parent</con:authProfile>
    </con:entry>
    <con:entry environmentId="0fbe5b0b-a38f-4b5d-a073-1256bff7bd99">
      <con:authProfile>Inherit From Parent</con:authProfile>
    </con:entry>
  </con:environmentSpec>
</con:testCase>
